ix_aims/__init__.py
ix_aims/cli.py
ix_aims/imgs/__init__.py
ix_aims/imgs/plusTab.png
ix_aims/imgs/processesBtn.png
ix_aims/imgs/yesBtn.png
ix_aims/lib.py
ix_aims-0.3.0.dist-info/entry_points.txt
ix_aims-0.3.0.dist-info/METADATA
ix_aims-0.3.0.dist-info/WHEEL
ix_aims-0.3.0.dist-info/RECORD
